{"AR02YGA1187B9B8AC4": "rock", "AR035N21187FB3938E": "rock", "AR03BDP1187FB5B324": "rock", "AR040QX1187FB4CFE1": "metal", "AR048JZ1187B9AEB85": "pop", "AR050VJ1187B9B13A7": "punk", "AR0KBXO1187B996460": "metal", "AR0OQPL1187B9B549A": "gospel", "AR0S7TA1187FB4D024": "pop", "AR0V36F1187FB366B1": "folk", "AR0WCZW1187B99F592": "pop", "AR10USD1187B99F3F1": "metal", "AR11YQ81187FB3C654": "country", "AR190KO1187B9905EC": "rock", "AR1PRQ21187FB3B481": "rock", "AR1Q25M1187B9B0D73": "hip hop", "AR2AGLK1187B9AAAD0": "rock", "AR2FAMK1187FB4CF60": "punk", "AR3MSAN1187B98F06B": "rock", "AR3Q48J1187FB55278": "rock", "AR4B3RX1187B9A868A": "soundtrack", "AR4OU721187FB4549D": "pop", "AR4R1FL1187FB55C3B": "rock", "AR5KOSW1187FB35FF4": "pop", "AR6892W1187B9AC71B": "rock", "AR6G4V01187B9AD086": "rock", "AR6I54S1187FB48C6B": "rock", "AR6J3X81187FB59A7B": "other", "AR6XPWV1187B9ADAEB": "rock", "AR7DBMA1187FB516B1": "rock", "AR7IYVY1187B9A2648": "electronic", "AR7N7MI1187FB46935": "soul", "AR7NNKG1187FB4AA1C": "rock", "AR7Q0O91187FB4DBE7": "hip hop", "AR7ZI7Z1187B98BF55": "celtic", "AR8BUVM1187FB4D94D": "rock", "AR8RXRI1187FB4104B": "hip hop", "AR8V1WA1187B9AD9E9": "rock", "AR9O98A1187FB39621": "rock", "AR9ST641187B99B4DE": "jazz", "ARA3I0J1187FB57869": "rock", "ARA6BH81187B98F3AF": "electronic", "ARABFU01187FB46712": "rock", "ARAIJG51187B9B97A4": "pop", "ARAMIDF1187FB3D8D4": "rock", "ARB6OGR1187FB4D43D": "electronic", "ARBD4QW1187FB42153": "metal", "ARBEBBY1187B9B43DB": "rock", "ARCJKV91187FB46210": "rock", "ARD2HR71187B99548F": "soul", "ARDQ62L1187FB56FF0": "rock", "ARDQ9AP1187B9BA3F6": "metal", "ARDSWIE1187FB39056": "hip hop", "ARE8GLF1187FB52532": "rock", "AREENKN1187B98F35D": "punk", "AREHK7O1187B9ADDD7": "pop", "AREN1A11187FB527EF": "country", "ARF2EHS1187B994F4E": "rock", "ARF6ZTO1187FB3684F": "metal", "ARFVYJI1187B9B8E13": "rock", "ARG9CID1187B9AB010": "punk", "ARGVJPK1187B9909EA": "rock", "ARH6W4X1187B99274F": "rock", "ARHRY5S1187B99B96F": "rock", "ARHUC691187B9AD27F": "metal", "ARI4S0E1187B9B06C0": "celtic", "ARIRCA31187FB58E84": "rock", "ARIW1BH1187FB4C94A": "electronic", "ARJGIOD1187B9AE920": "pop", "ARJV0U41187B9AB715": "rock", "ARKMIBT11F4C8430D9": "pop", "ARKQQZA12086C116FC": "hip hop", "ARKR75V1187FB3D4D5": "rock", "ARL635X1187B990092": "electronic", "ARLTWXK1187FB5A3F8": "jazz", "ARLUF1T1187FB3603B": "rock", "ARM0P6Z1187FB4D466": "rock", "ARMG34A1187FB548A8": "rock", "ARML3X41187FB35F2E": "rock", "ARMRCET1187FB52049": "pop", "ARMW4I01187B98AEF8": "hip hop", "ARN2ZKL1187FB3972B": "rock", "ARN5L1O1187FB4D955": "metal", "ARN6M7I1187FB4DEAF": "metal", "ARN8NCB1187FB49652": "other", "ARNDL191187FB51583": "rock", "ARNNM56119B86686EA": "country", "ARNNQBT1187FB437C1": "metal", "ARNRPI31187B9AC699": "electronic", "AROBSHL1187B9AFB01": "metal", "ARPFHN61187FB575F6": "hip hop", "ARPGTHP1187B9AC284": "metal", "ARPKATM1187B9B76E6": "rock", "ARQATWU1187B98EE26": "metal", "ARQEPTZ1187FB4CD36": "hip hop", "ARQUMH41187B9AF699": "metal", "ARQXC7V1187FB4DA9E": "rock", "ARR3ONV1187B9A2F59": "rock", "ARRDRI71187FB46EAA": "rock", "ARRH63Y1187FB47783": "hip hop", "ARRI5MR1187FB47CAB": "jazz", "ARRJ3UC1187FB579D7": "rock", "ARRJNTE1187FB44E12": "rock", "ARRXG5Y1187B9AA016": "hip hop", "ARSG7NQ1187FB57482": "rock", "ARSL3N21187B98DFC5": "rock", "ARTH9041187FB43E1F": "rock", "ARTXGGI1187B9B3D58": "rock", "ARU9KWP1187B98B2A7": "hip hop", "ARUKN9H1187B9B71C8": "rock", "ARUTEVU1187B9ACAF9": "rock", "ARUWB5W1187B98D7A1": "metal", "ARVG4OK1187B9B6BD3": "rock", "ARVXU2X1187B9AE6D8": "metal", "ARVXV1J1187FB5BF88": "rock", "ARW9FP41187B98C2A7": "folk", "ARWA8AH1187FB3FC84": "rock", "ARWD3OC1187FB3A666": "rock", "ARXG6L11187FB5695E": "other", "ARXOTQH1187FB57084": "pop", "ARYG6CU1187FB3852B": "electronic", "ARYLSGC11F43A69EF6": "rock", "ARYO9BU1187B9ADA88": "rock", "ARYVO9V1187B9B1FC6": "rock", "ARZ33PH1187FB52F58": "pop", "ARZENOX1187B98A645": "pop", "ARZWK2R1187B98F09F": "rock"}